model_providers/__init__.py
model_providers/__main__.py
model_providers/_compat.py
model_providers/_files.py
model_providers/_models.py
model_providers/_types.py
model_providers/_utils/__init__.py
model_providers/_utils/_transform.py
model_providers/_utils/_typing.py
model_providers/_utils/_utils.py
model_providers/bootstrap_web/entities/__init__.py
model_providers/bootstrap_web/entities/model_provider_entities.py
model_providers/bootstrap_web/message_convert/__init__.py
model_providers/bootstrap_web/message_convert/core.py
model_providers/bootstrap_web/openai_bootstrap_web.py
model_providers/core/bootstrap/__init__.py
model_providers/core/bootstrap/base.py
model_providers/core/bootstrap/bootstrap_register.py
model_providers/core/bootstrap/openai_protocol.py
model_providers/core/bootstrap/providers_wapper.py
model_providers/core/entities/__init__.py
model_providers/core/entities/agent_entities.py
model_providers/core/entities/message_entities.py
model_providers/core/entities/model_entities.py
model_providers/core/entities/provider_configuration.py
model_providers/core/entities/provider_entities.py
model_providers/core/entities/queue_entities.py
model_providers/core/model_manager.py
model_providers/core/model_runtime/README.md
model_providers/core/model_runtime/README_en.md
model_providers/core/model_runtime/__init__.py
model_providers/core/model_runtime/callbacks/__init__.py
model_providers/core/model_runtime/callbacks/base_callback.py
model_providers/core/model_runtime/callbacks/logging_callback.py
model_providers/core/model_runtime/docs/en_US/images/index/img.png
model_providers/core/model_runtime/docs/en_US/interfaces.md
model_providers/core/model_runtime/docs/en_US/provider_scale_out.md
model_providers/core/model_runtime/docs/en_US/schema.md
model_providers/core/model_runtime/docs/zh_Hans/customizable_model_scale_out.md
model_providers/core/model_runtime/docs/zh_Hans/images/index/img.png
model_providers/core/model_runtime/docs/zh_Hans/interfaces.md
model_providers-0.3.1.dist-info/METADATA
model_providers-0.3.1.dist-info/WHEEL
model_providers-0.3.1.dist-info/entry_points.txt
model_providers-0.3.1.dist-info/RECORD
