Metadata-Version: 2.1
Name: model-providers
Version: 0.3.1
Summary: 
Author: glide-the
Author-email: z2533736852@gmail.com
Requires-Python: >=3.8, !=2.7.*, !=3.0.*, !=3.1.*, !=3.2.*, !=3.3.*, !=3.4.*, !=3.5.*, !=3.6.*, !=3.7.*, !=3.12.*
Classifier: Programming Language :: Python :: 3
Classifier: Programming Language :: Python :: 3.9
Classifier: Programming Language :: Python :: 3.10
Classifier: Programming Language :: Python :: 3.11
Requires-Dist: boto3 (>=1.28.17,<1.29.0)
Requires-Dist: fastapi (>=0.109.2,<0.110.0)
Requires-Dist: omegaconf (>=2.0.6,<2.1.0)
Requires-Dist: openai (>=1.13.3,<1.14.0)
Requires-Dist: pydantic (>=2.6.4,<2.7.0)
Requires-Dist: pydub (>=0.25.1,<0.26.0)
Requires-Dist: pyyaml (>=6.0.1,<6.1.0)
Requires-Dist: sse-starlette (>=1.8.2,<1.9.0)
Requires-Dist: tiktoken (>=0.7.0)
Requires-Dist: transformers (>=4.31.0,<4.32.0)
Requires-Dist: uvicorn (>=0.27.0.post1)
